[
  {
    "region": "BBC Mundo",
    "texto": "\"Me da miedo lo que voy a ver allá dentro\": BBC Mundo visita la morgue improvisada de Los Silos, donde los cadáveres se acumulan al aire libre tras los terremotos en Venezuela"
  },
  {
    "region": "BBC Mundo",
    "texto": "El mapa satelital que muestra la magnitud de la destrucción en La Guaira, la zona más afectada por los terremotos de Venezuela"
  },
  {
    "region": "BBC Mundo",
    "texto": "3 factores que explican por qué se derrumbaron tantos edificios en La Guaira por el terremoto en Venezuela"
  },
  {
    "region": "BBC Mundo",
    "texto": "\"¡Un milagro!\": el extraordinario rescate de Hernán, el hombre que estuvo 8 días bajo los escombros tras los terremotos en Venezuela"
  },
  {
    "region": "BBC Mundo",
    "texto": "\"Gasté US$6.000 en un viaje para ver el Mundial y me dejaron tirado en la puerta del estadio\""
  }
]